LICENSE
README.md
setup.cfg
setup.py
lavviebot/__init__.py
lavviebot/constants.py
lavviebot/exceptions.py
lavviebot/lavviebot_client.py
lavviebot/model.py
lavviebotaio.egg-info/PKG-INFO
lavviebotaio.egg-info/SOURCES.txt
lavviebotaio.egg-info/dependency_links.txt
lavviebotaio.egg-info/requires.txt
lavviebotaio.egg-info/top_level.txt