Metadata-Version: 2.1
Name: lavviebotaio
Version: 0.3.0
Summary: Asynchronous Python library for the PurrSong API utilized by LavvieBot S litter boxes
Home-page: https://github.com/RobertD502/lavviebotaio
Author: Robert Drinovac
Author-email: unlisted@gmail.com
License: UNKNOWN
Project-URL: Bug Reports, https://github.com/RobertD502/lavviebotaio/issues
Project-URL: Source, https://github.com/RobertD502/lavviebotaio/
Keywords: lavviebot,lavviebot s,purrsong,litter box
Platform: UNKNOWN
Classifier: Programming Language :: Python :: 3
Classifier: License :: OSI Approved :: MIT License
Classifier: Operating System :: OS Independent
Requires-Python: >=3.9
